{
  "metaData": {
    "title": "Da! Ai ce vizita la Roșia Montană",
    "text": "Ne aflăm într-o zonă cu munți, văi și lacuri dar și cu o bogată încărcătură istorică și culturală datorată patrimoniului construit de diverse civilizații venite aici încă din antichitate pentru a extrage aur. Pentru a le descoperi oferim trasee ghidate, iar din fața casei pornesc 5 trasee marcate.",
    "img": "/assets/img/attractions/presentation/fullWidthImg.jpg"
  },
  "headline": {
    "title": "Ai ce vizita la Roșia Montană!",
    "videoSource": "",
    "img": "/assets/img/attractions/presentation/fullWidthImg.jpg"
  },
  "sections": [
    {
      "type": "title",
      "text": "<i class='far fa-star'></i> De văzut",
      "sectionId": "toSee",
      "addLinkInPageHeadline": true
    },
    {
      "type": "article",
      "specificArticles": [
        {
          "text": "Ne aflăm într-o zonă cu munți, văi și lacuri dar și cu o bogată încărcătură istorică și culturală datorată patrimoniului construit de diverse civilizații venite aici încă din antichitate pentru a extrage aur. Vezi mai jos o parte din acestea și te așteptăm la tururile ghidate ce le organizăm în zonă pentru a le vedea și descoperi povestea."
        },
        {
          "title": "Centrul istoric",
          "text": "Centrul Istoric al celei mai vechi localități atestate documentar din Romania, Rosia Montana anul 131, cuprinde diverse clădiri de patrimoniu (biserici și cimitire de 5 culte diferite, casele aurarilor, șteampuri, foste ateliere și institutii, Parohia Unitariana cu expozitii foto și obiecte mineresti iar din turnul bisericii o deosebita priveliste asupra satului). <br><i class='fa fa-map-signs'></i> <b>Cum ajung?</b> 10min drumeție - ",
          "seeAlso": [
            {
              "text": "vezi harta",
              "textOnMouseOver": "Click aici...",
              "link": "https://www.google.com/maps/dir/Casa+Petri+Rosia+Montana/Biserica+Sf%C3%A2ntul+Ladislau/Casa+Parohial%C4%83+Unitarian%C4%83/Hungarian+School/Biserica+Reformat%C4%83/Unit%C3%A1rius+Templom/Henes+House/Casa+Petri+Rosia+Montana/@46.3059856,23.1293956,17z/data=!3m1!4b1!4m50!4m49!1m5!1m1!1s0x474ecce046c99d41:0xc76f83a95070630c!2m2!1d23.129873!2d46.3065798!1m5!1m1!1s0x474ecce10e704519:0x94199c2736e92711!2m2!1d23.1306276!2d46.3046896!1m5!1m1!1s0x474ecce0f01d4e81:0x458d5ae506f0947a!2m2!1d23.1319164!2d46.3060024!1m5!1m1!1s0x474ecce092b4f77b:0x72b9cddd9b85f2f9!2m2!1d23.1324407!2d46.3064907!1m5!1m1!1s0x474ecce0ecbdf039:0xd38d55a33c6c279!2m2!1d23.1326285!2d46.3063647!1m5!1m1!1s0x474ecce0e71be01f:0x7aeb513d073f4f6d!2m2!1d23.132379!2d46.3056458!1m5!1m1!1s0x474ecce09b7ef661:0xfacaac828a00c789!2m2!1d23.1332132!2d46.307254!1m5!1m1!1s0x474ecce046c99d41:0xc76f83a95070630c!2m2!1d23.129873!2d46.3065798!3e2?hl=en-US"
            }
          ],
          "images": [
            {
              "text": "Ornamentele clădirilor de patrimoniu.",
              "thumbnail": "assets/img/attractions/article/sicilianStreet/thumbnail/ornamente.jpg",
              "fullSize": "assets/img/attractions/article/sicilianStreet/fullSize/ornamente.jpg"
            },
            {
              "text": "Bisericile din centrul istoric (romano-catolica, unitariană și calvină).",
              "thumbnail": "assets/img/attractions/article/sicilianStreet/thumbnail/4.jpg",
              "fullSize": "assets/img/attractions/article/sicilianStreet/fullSize/4.jpg"
            },
            {
              "text": "Școala Germană și casele aurarilor - cartierului german",
              "thumbnail": "assets/img/attractions/article/panoramicBench/thumbnail/1.jpg",
              "fullSize": "assets/img/attractions/article/panoramicBench/fullSize/1.jpg"
            }
          ]
        },
        {
          "title": "Muzeul Mineritului",
          "text": "La Muzeul Mineritului ROSIAMIN se pot vizita o parte din galeriile romane, expoziții foto, șteampuri și alte obiecte folosite în industria minieră. <br><i class='fa fa-map-signs'></i> <b>Cum ajung?</b> 15min drumeție - ",
          "seeAlso": [
            {
              "text": "vezi harta",
              "textOnMouseOver": "Click aici...",
              "link": "https://www.google.com/maps/dir/Casa+Petri+Rosia+Montana/Muzeul+Mineritului+Galeriile+Romane,+Ro%C8%99ia+Montan%C4%83,+Rom%C3%A2nia/@46.3042362,23.1182099,16.04z/data=!4m14!4m13!1m5!1m1!1s0x474ecce046c99d41:0xc76f83a95070630c!2m2!1d23.129873!2d46.3065798!1m5!1m1!1s0x474ecd1ba8291199:0x3f86ed8bb68ce1d3!2m2!1d23.1147891!2d46.3046869!3e2?hl=en-US"
            }
          ],
          "images": [
            {
              "text": "<b>Galeriile Romane</b> - Pentru a le vizita se coboara 157 de trepte in subteran.",
              "thumbnail": "assets/img/attractions/article/romanGalleries/thumbnail/1.jpg",
              "fullSize": "assets/img/attractions/article/romanGalleries/fullSize/1.jpg"
            },
            {
              "text": "<b>Muzeul Mineritului</b> - instalații folosite în prelucrarea aurului.",
              "thumbnail": "assets/img/attractions/article/romanGalleries/thumbnail/2.jpg",
              "fullSize": "assets/img/attractions/article/romanGalleries/fullSize/2.jpg"
            },
            {
              "text": "Langă muzeu se află o biserică cu o legendă deosebită, construită în urma unui pact dintre un miner și vâlva (spiritele galeriilor). Aflați povestea acolo..",
              "thumbnail": "assets/img/attractions/article/churches/orthodoxChurch/thumbnail/1.jpg",
              "fullSize": "assets/img/attractions/article/churches/orthodoxChurch/fullSize/1.jpg"
            }
          ]
        },
        {
          "title": "Galeriile aurifere",
          "text": "Roșia Montană deține una din <b>cele mai extinse complexe de mine aurifere din lume</b>, un labirint subteran de peste 120km format din galerii romane, preromane sau habsburgice. Recomandăm vizitarea acestora împreună cu un ghid!",
          "images": [
            {
              "text": "Galerii din perioada habsburgică.",
              "thumbnail": "assets/img/attractions/article/vaidoaiaGalleries/thumbnail/prietenie.jpg",
              "fullSize": "assets/img/attractions/article/vaidoaiaGalleries/fullSize/prietenie.jpg"
            },
            {
              "text": "Galerii din perioada romană.",
              "thumbnail": "assets/img/attractions/article/carnic/galleries/thumbnail/zeus-galerii-romane-carnic-oriz-rosia.jpg",
              "fullSize": "assets/img/attractions/article/carnic/galleries/fullSize/zeus-galerii-romane-carnic-oriz-rosia.jpg"
            },
            {
              "text": "Galerii Cetate.",
              "thumbnail": "assets/img/attractions/article/carnic/galleries/thumbnail/zeus-galerii-carnic-coranda-mare-rosia.jpg",
              "fullSize": "assets/img/attractions/article/carnic/galleries/fullSize/zeus-galerii-carnic-coranda-mare-rosia.jpg"
            },
            {
              "text": "Galerii Carnic.",
              "thumbnail": "assets/img/attractions/article/carnic/galleries/thumbnail/galerii-romane-carnic.jpg",
              "fullSize": "assets/img/attractions/article/carnic/galleries/fullSize/galerii-romane-carnic.jpg"
            }
          ]
        },
        {
          "title": "Monumentele Naturii",
          "text": "Masivele din zonă (Cârnic, Șulei, Orlea și Rotundu) dețin diverse obiective naturale ce merită vizitate. <br><i class='fa fa-map-signs'></i> <b>Cum ajung?</b> 3h drumeție - traseul punct roșu - ",
          "seeAlso": [
            {
              "text": "vezi harta",
              "textOnMouseOver": "Click aici...",
              "link": "https://www.google.com/maps/dir/Casa+Petri+Rosia+Montana/Piatra+Corbului,+DJ742,+Romania/Sphinx+Rosia+Montana,+DJ742,+Romania/Lety,+Romania/%C5%9Eulei,+Romania/Casa+Petri+Rosia+Montana/@46.3042925,23.1321371,15z/data=!3m1!4b1!4m38!4m37!1m5!1m1!1s0x474ecce046c99d41:0xc76f83a95070630c!2m2!1d23.129873!2d46.3065798!1m5!1m1!1s0x474ecce561ec13df:0x539a9c4dab922dfa!2m2!1d23.1359679!2d46.2984078!1m5!1m1!1s0x474ecce4edad3383:0x29e3550fad11d5cf!2m2!1d23.1315449!2d46.2995661!1m5!1m1!1s0x474eccc2f30949c7:0xcd02b53d4411b695!2m2!1d23.1460047!2d46.3062535!1m5!1m1!1s0x474ecce9fc29064d:0xb5e35f18787dc75!2m2!1d23.148247!2d46.3041856!1m5!1m1!1s0x474ecce046c99d41:0xc76f83a95070630c!2m2!1d23.129873!2d46.3065798!3e2?hl=en-US"
            }
          ],
          "images": [
            {
              "text": "<b>Piatra Corbului</b> - rezervație naturală protejată. Galeriile de aici sunt unele din cele mai vechi din Roșia Montană, făcute de agatârși folosind doar apă și foc",
              "thumbnail": "assets/img/attractions/article/carnic/ravenStone/thumbnail/1.jpg",
              "fullSize": "assets/img/attractions/article/carnic/ravenStone/fullSize/1.jpg"
            },
            {
              "text": "<b>Sfinxul Cârnic</b> - Crucea de pe Sfinx a fost pusă aici de baieși (mineri) pentru a fi călauziți în mină când căutau aur.",
              "thumbnail": "assets/img/attractions/article/carnic/sphinx/thumbnail/1.jpg",
              "fullSize": "assets/img/attractions/article/carnic/sphinx/fullSize/1.jpg"
            },
            {
              "text": "<b>Masivul Sulei</b> - creasta masivului Sulei este îngustă dându-ți impresia că mergi pe o frânghie pe care trebuie să îți menții echilibrul.",
              "thumbnail": "assets/img/attractions/article/letySulei/thumbnail/1.jpg",
              "fullSize": "assets/img/attractions/article/letySulei/fullSize/1.jpg"
            },
            {
              "text": "Stalagnitele galeriilor aurifere.",
              "thumbnail": "assets/img/attractions/article/carnic/stalagnite/thumbnail/stalagnite-carnic-rosia.jpg",
              "fullSize": "assets/img/attractions/article/carnic/stalagnite/fullSize/stalagnite-carnic-rosia.jpg"
            }
          ]
        },
        {
          "title": "Tăurile",
          "text": "Peste 100 de tăuri au fost construite în perioada habsburgică pentru a ajuta la prelucrarea aurului, dar acum au mai rămas doar 7. <br><i class='fa fa-map-signs'></i> <b>Cum ajung?</b> 3h drumeție - traseul punct albastru - ",
          "seeAlso": [
            {
              "text": "vezi harta",
              "textOnMouseOver": "Click aici...",
              "link": "https://www.google.com/maps/dir/Casa+Petri+Rosia+Montana,+Historical+center,+nr.+331A,+Ro%C8%99ia+Montan%C4%83+517615,+Romania/T%C4%83ul+%C8%9Aarinii,+Romania/T%C4%83ul+Mare,+Romania/T%C4%83ul+Corna,+Romania/T%C4%83ul+Brazi,+Romania/Casa+Petri+Rosia+Montana,+Historical+center,+nr.+331A,+Ro%C8%99ia+Montan%C4%83+517615,+Romania/@46.3074897,23.1154043,14z/data=!3m1!4b1!4m38!4m37!1m5!1m1!1s0x474ecce046c99d41:0xc76f83a95070630c!2m2!1d23.129873!2d46.3065798!1m5!1m1!1s0x474ecd247983fa01:0x2a7cbd6966533f77!2m2!1d23.1239666!2d46.3150817!1m5!1m1!1s0x474eccdb6ec7fe37:0xe4b1c3880d788b47!2m2!1d23.1445582!2d46.3111615!1m5!1m1!1s0x474eccf02d4e329d:0xd861c7426bfe18e8!2m2!1d23.1380803!2d46.2959598!1m5!1m1!1s0x474ecce619e80185:0x30e1fffe6d4c032c!2m2!1d23.1387897!2d46.3024415!1m5!1m1!1s0x474ecce046c99d41:0xc76f83a95070630c!2m2!1d23.129873!2d46.3065798!3e2?hl=en-US"
            }
          ],
          "images": [
            {
              "text": "<b>Tăul Țarinii</b> - un mic lac de munte superb pe timp de toamnă.",
              "thumbnail": "assets/img/attractions/article/lakes/tariniLake/thumbnail/1.jpg",
              "fullSize": "assets/img/attractions/article/lakes/tariniLake/fullSize/1.jpg"
            },
            {
              "text": "Tăul Mare sau Tăul inimă (datorită formei lui).",
              "thumbnail": "assets/img/attractions/article/lakes/bigLake/thumbnail/10.jpg",
              "fullSize": "assets/img/attractions/article/lakes/bigLake/fullSize/10.jpg"
            },
            {
              "text": "<b>Tăul Brazi</b> - Casa este a unui pictor care folosește priveliștea ca sursă de inspirație. ",
              "thumbnail": "assets/img/attractions/article/lakes/braziLake/thumbnail/1.jpg",
              "fullSize": "assets/img/attractions/article/lakes/braziLake/fullSize/1.jpg"
            }
          ]
        },
        {
          "title": "Puncte de belvedere",
          "text": "Locuri cu priveliști deosebite, natură, liniște, relaxare și aer curat.",
          "images": [
            {
              "text": "Punct de belvedere masivul Cârnic.",
              "thumbnail": "assets/img/attractions/article/carnic/carnic/thumbnail/natura-flori-vara-carnic-ceata-rosia-montana.jpg",
              "fullSize": "assets/img/attractions/article/carnic/carnic/fullSize/natura-flori-vara-carnic-ceata-rosia-montana.jpg"
            },
            {
              "text": "Punct de belvedere Tăuri.",
              "thumbnail": "assets/img/attractions/article/carnic/carnic/thumbnail/tauri-carnic-natura-rosia-montana.jpg",
              "fullSize": "assets/img/attractions/article/carnic/carnic/fullSize/tauri-carnic-natura-rosia-montana.jpg"
            },
            {
              "text": "Punct de belvedere Valea Roșiei.",
              "thumbnail": "assets/img/attractions/article/vaidoaiaGalleries/thumbnail/fog-ceata-rosia-montana-vaidoaia-primavara.jpg",
              "fullSize": "assets/img/attractions/article/vaidoaiaGalleries/fullSize/fog-ceata-rosia-montana-vaidoaia-primavara.jpg"
            }
          ]
        },
        {
          "title": "Cariera de aur Cetate",
          "text": "Un alt tip de exploatări de aur ce pot fi vizitate sunt cele de suprafață. Numele carierei 'Cetate' vine de la faptul că aici era într-adevăr o cetate sculptată în munți de către daci si romani cu rol de apărare, distrusă în perioada comunismului pentru a extrage aurul de sub ea. <br><i class='fa fa-map-signs'></i> <b>Cum ajung?</b> 30min drumeție - traseul punct roșu -  ",
          "seeAlso": [
            {
              "text": "vezi harta",
              "textOnMouseOver": "Click aici...",
              "link": "https://www.google.com/maps/dir/Casa+Petri+Rosia+Montana,+Historical+center,+nr.+331A,+Ro%C8%99ia+Montan%C4%83+517615,+Romania/Cariera+Cetate,+Rom%C3%A2nia/@46.3021807,23.1215599,16z/data=!3m1!4b1!4m14!4m13!1m5!1m1!1s0x474ecce046c99d41:0xc76f83a95070630c!2m2!1d23.129873!2d46.3065798!1m5!1m1!1s0x474eccfd7a6c9121:0x8693e5c31797f180!2m2!1d23.1210709!2d46.2979371!3e2?hl=en-US"
            }
          ],
          "images": [
            {
              "text": "Cariera Cetate",
              "thumbnail": "assets/img/attractions/article/carnic/cetatePit/thumbnail/cariera.jpg",
              "fullSize": "assets/img/attractions/article/carnic/cetatePit/fullSize/cariera.jpg"
            },
            {
              "text": "Galeriile din Cariera Cetate",
              "thumbnail": "assets/img/attractions/article/carnic/cetatePit/thumbnail/galerii.jpg",
              "fullSize": "assets/img/attractions/article/carnic/cetatePit/fullSize/galerii.jpg"
            }
          ]
        },
        {
          "title": "Geamăna și Roșia Poieni",
          "text": "Cariera de Cupru Roșia Poieni este una din cele mai mari cariere de suprafață din Europa, mândria sistemului comunist, 5000 de tone de cupru producție anuală, utilaje imense și sute de locuri de muncă, dar toate acestea au avut consecințe asupra mediului: un munte ras, vegetație distrusă, sol arid, utilaje abandonate, iar sterilul rezultat a fost deversat în aval peste satul Geamăna formand un iaz de decantare vizibil și din satelit. <br><i class='fa fa-map-signs'></i> <b>Cum ajung?</b> 3h drumeție (1h cu mașina) - ",
          "seeAlso": [
            {
              "text": "vezi harta",
              "textOnMouseOver": "Click aici...",
              "link": "https://www.google.ro/maps/dir/Casa+Petri,+DC146,+Ro%C8%99ia+Montan%C4%83/Geam%C4%83na/@46.3430812,23.1073464,12.49z/data=!4m14!4m13!1m5!1m1!1s0x474ecce046c99d41:0xc76f83a95070630c!2m2!1d23.129873!2d46.3065798!1m5!1m1!1s0x4749335e58fe877f:0x883a3e3ec5d25d8a!2m2!1d23.2042788!2d46.3299984!3e0?hl=ro"
            }
          ],
          "images": [
            {
              "text": "<b>Cariera de Cupru Roșia Poieni</b> are 24 de trepte de exploatare, fiecare de 15m înălțime.",
              "thumbnail": "assets/img/attractions/article/copperPit/thumbnail/1.jpg",
              "fullSize": "assets/img/attractions/article/copperPit/fullSize/1.jpg"
            },
            {
              "text": "Foste gospoddării din satul Geamăna",
              "thumbnail": "assets/img/attractions/article/lakes/geamana/thumbnail/2.jpg",
              "fullSize": "assets/img/attractions/article/lakes/geamana/fullSize/2.jpg"
            },
            {
              "text": "Turla bisericii din fostul sat Geamăna, acoperit acum de iazul de decantare.",
              "thumbnail": "assets/img/attractions/article/lakes/geamana/thumbnail/1.jpg",
              "fullSize": "assets/img/attractions/article/lakes/geamana/fullSize/1.jpg"
            }
          ]
        },
        {
          "title": "Campania Salvați Roșia Montană",
          "text": "Vizitați locurile unde timp de 15 ani au avut loc acțiuni împotriva companiei canadiene ce dorea o mare exploatare cu cianuri la Roșia Montană. Proiectul a fost oprit în urma unor ample proteste de stradă în marile orașe din România și diasporă (peste 60 de mii de oameni) <br><i class='fa fa-map-signs'></i> <b>Cum ajung?</b> 30min drumeție -  ",
          "seeAlso": [
            {
              "text": "vezi harta",
              "textOnMouseOver": "Click aici...",
              "link": "https://www.google.com/maps/dir/Casa+Petri+Rosia+Montana,+Historical+center,+nr.+331A,+Ro%C8%99ia+Montan%C4%83+517615,+Romania/Sculpturi+Calcar+Eugen+David,+DC147,+Ro%C8%99ia+Montan%C4%83,+Romania/@46.3096245,23.121467,16.26z/data=!4m14!4m13!1m5!1m1!1s0x474ecce046c99d41:0xc76f83a95070630c!2m2!1d23.129873!2d46.3065798!1m5!1m1!1s0x474ecd18f7143d2b:0x3c28cea5fbc21b20!2m2!1d23.1183431!2d46.3089531!3e2?hl=en-US"
            }
          ],
          "images": [
            {
              "text": "Ferma lui David Eugen - aici au început multe acțiuni pentru salvarea Roșiei Montane. Un ONG din Paris a realizat sculpturile - aflați acolo povestea lor.",
              "thumbnail": "assets/img/attractions/article/sculpture/thumbnail/1.jpg",
              "fullSize": "assets/img/attractions/article/sculpture/fullSize/1.jpg"
            },
            {
              "text": "Reduta de pe Țarină - locul unde anual se organiza festivalul de mediu și activism FânFest",
              "thumbnail": "assets/img/attractions/article/fanfest/thumbnail/fanfest.jpg",
              "fullSize": "assets/img/attractions/article/fanfest/fullSize/fanfest.jpg"
            }
          ]
        },
        {
          "title": "Detunata",
          "text": "Masivul este o arie protejată formată din coloane de bazalt de 80m înalțime la baza căruia s-a format o mare de blocuri de piatră printre care uneori apare un mic ghețar. Aici a trait și Fefeleaga (personajul lui Agârbiceanu), zona are legende impresionante, oamenii sunt primitori și alocuri se vând plăcinte cu brânză delicioase. <br><i class='fa fa-map-signs'></i> <b>Cum ajung?</b> 3h drumeție - traseul cruce roșie - ",
          "seeAlso": [
            {
              "text": "vezi harta",
              "textOnMouseOver": "Click aici...",
              "link": "https://www.google.com/maps/dir/Casa+Petri+Rosia+Montana,+Historical+center,+nr.+331A,+Ro%C8%99ia+Montan%C4%83+517615,+Romania/Detunata+Goal%C4%83,+DC117,+Romania/@46.2932066,23.1479595,14z/data=!3m1!4b1!4m14!4m13!1m5!1m1!1s0x474ecce046c99d41:0xc76f83a95070630c!2m2!1d23.129873!2d46.3065798!1m5!1m1!1s0x474ecb0b3fc6fdbf:0x625d95e7bb6b2e0f!2m2!1d23.1967854!2d46.2772531!3e2?hl=en-US"
            }
          ],
          "images": [
            {
              "text": "Detunata.",
              "thumbnail": "assets/img/attractions/article/detunata/thumbnail/detunata3.jpg",
              "fullSize": "assets/img/attractions/article/detunata/fullSize/detunata3.jpg"
            },
            {
              "text": "Priveliștea de pe Detunata - spre ținutul Moților.",
              "thumbnail": "assets/img/attractions/article/detunata/thumbnail/lumea.jpg",
              "fullSize": "assets/img/attractions/article/detunata/fullSize/lumea.jpg"
            },
            {
              "text": "Detunata - marea de bazalt (vederea din vârf).",
              "thumbnail": "assets/img/attractions/article/detunata/thumbnail/detunata-pietre-jos-brazi.jpg",
              "fullSize": "assets/img/attractions/article/detunata/fullSize/detunata-pietre-jos-brazi.jpg"
            }
          ]
        },
        {
          "title": "Muzeul Buciumanilor",
          "text": "Lângă Roșia Montană se află un alt loc cu vechi galerii aurifere, istorie și patrimoniu. Vizitați Muzeul Buciumanilor din centrul satului Bucium Poieni.",
          "seeAlso": [
            {
              "text": "<br><i class='fa fa-map-signs'></i> <b>Cum ajung?</b> 30min cu mașina - vezi harta",
              "textOnMouseOver": "Click aici...",
              "link": "https://www.google.ro/maps/dir/Casa+Petri+Rosia+Montana,+Historical+center,+nr.+331A,+Ro%C8%99ia+Montan%C4%83+517615/Muzeul+Buciumanilor,+Poieni/@46.2855654,23.0514532,11.54z/data=!4m14!4m13!1m5!1m1!1s0x474ecce046c99d41:0xc76f83a95070630c!2m2!1d23.129873!2d46.3065798!1m5!1m1!1s0x474ecb60f701d409:0xfec892598003f6c4!2m2!1d23.1987534!2d46.2520053!3e0?hl=ro"
            },
            {
              "text": "<br> Vezi aici contact și program",
              "textOnMouseOver": "Click aici...",
              "link": "http://www.baiadomnilor.ro/ullamcorper-cras-aenean"
            }
          ],
          "images": [
            {
              "text": "Articole folosite în minerit - Șteamp.",
              "thumbnail": "assets/img/attractions/article/muzeulBuciumanilor/thumbnail/weaming-loom-razboi-de-cusut.jpg",
              "fullSize": "assets/img/attractions/article/muzeulBuciumanilor/fullSize/weaming-loom-razboi-de-cusut.jpg"
            },
            {
              "text": "Articole folosite in casa - razboi de tesut",
              "thumbnail": "assets/img/attractions/article/muzeulBuciumanilor/thumbnail/steamp-minerit-bucium-muzeu.jpg",
              "fullSize": "assets/img/attractions/article/muzeulBuciumanilor/fullSize/steamp-minerit-bucium-muzeu.jpg"
            }
          ]
        },
        {
          "title": "Muzeul aurului Brad",
          "text": "Vedeți cum arată aurul nativ neprelucrat extras din Roșia Montană și alte locuri ale patrulaterul aurifer Apuseni. <br><i class='fa fa-map-signs'></i> <b>Cum ajung?</b> 1h cu mașina - ",
          "seeAlso": [
            {
              "text": "vezi harta",
              "textOnMouseOver": "Click aici...",
              "link": "https://www.google.fr/maps/dir/Casa+Petri+Rosia+Montana,+Ro%C8%99ia+Montan%C4%83,+Romania/Gold+Museum+Brad,+Strada+Independen%C8%9Bei+3,+Brad+335200,+Romania/@46.2132086,22.8208342,11z/data=!3m1!4b1!4m13!4m12!1m5!1m1!1s0x474ecce046c99d41:0xc76f83a95070630c!2m2!1d23.129873!2d46.3065798!1m5!1m1!1s0x474edc27fe255555:0x38ae2fbee961bb90!2m2!1d22.7909237!2d46.1290106"
            }
          ],
          "images": [
            {
              "text": "Exponate de aur Muzeul Aurului Brad.",
              "thumbnail": "assets/img/attractions/article/bradGoldMuseum/thumbnail/aurBrad1.jpg",
              "fullSize": "assets/img/attractions/article/bradGoldMuseum/fullSize/aurBrad1.jpg"
            },
            {
              "text": "Exponate de aur Muzeul Aurului Brad.",
              "thumbnail": "assets/img/attractions/article/bradGoldMuseum/thumbnail/aurBrad2.jpg",
              "fullSize": "assets/img/attractions/article/bradGoldMuseum/fullSize/aurBrad2.jpg"
            }
          ]
        },
        {
          "title": "Ghețarul Scărișoara",
          "text": "Pestera din inima Apusenilor gazduieste cel mai mare ghețar subteran din lume și este prima peșteră din Romania declarata monument al naturii (1938). <br><i class='fa fa-map-signs'></i> <b>Cum ajung?</b> 1h cu mașina - ",
          "seeAlso": [
            {
              "text": "vezi harta",
              "textOnMouseOver": "Click aici...",
              "link": "https://www.google.com/maps/dir/Casa+Petri+Rosia+Montana,+Historical+center,+nr.+331A,+Ro%C8%99ia+Montan%C4%83+517615,+Romania/Glacier+Cave+Scarisoara,+Romania/@46.3962379,22.8293194,11z/data=!3m1!4b1!4m14!4m13!1m5!1m1!1s0x474ecce046c99d41:0xc76f83a95070630c!2m2!1d23.129873!2d46.3065798!1m5!1m1!1s0x4748d16f214d425f:0x3c356cdce6edf2d6!2m2!1d22.8107369!2d46.4898586!3e0?hl=en-US"
            }
          ],
          "images": [
            {
              "text": "Drumul spre Ghețarul Scărișoara",
              "thumbnail": "assets/img/attractions/article/scarisoaraRoad/thumbnail/1.jpg",
              "fullSize": "assets/img/attractions/article/scarisoaraRoad/fullSize/1.jpg"
            },
            {
              "text": "Peștera Scărișoara",
              "thumbnail": "assets/img/attractions/article/scarisoara/thumbnail/1.jpg",
              "fullSize": "assets/img/attractions/article/scarisoara/fullSize/1.jpg"
            },
            {
              "text": "Ghețarul Scărișoara",
              "thumbnail": "assets/img/attractions/article/scarisoara/thumbnail/2.jpg",
              "fullSize": "assets/img/attractions/article/scarisoara/fullSize/2.jpg"
            }
          ]
        },
        {
          "title": "Poiana cu narcise",
          "text": "Narcisele înfloresc în luna Mai și țin toată primăvara. Mirosul din acestă poiană e ceva ce nu veți uita niciodată. <br><i class='fa fa-map-signs'></i> <b>Cum ajung?</b> 3h drumeție (1h cu mașina) - ",
          "seeAlso": [
            {
              "text": "vezi harta",
              "textOnMouseOver": "Click aici...",
              "link": "https://www.google.com/maps/dir/Casa+Petri+Rosia+Montana,+Historical+center,+nr.+331A,+Ro%C8%99ia+Montan%C4%83+517615,+Romania/Gura+Ro%C8%99iei,+Romania/Abrud,+Rom%C3%A2nia/Poiana+cu+Narcise+de+la+Negrileasa,+Valea+Negrilesii,+Romania/@46.2578286,23.0861823,12.26z/data=!4m26!4m25!1m5!1m1!1s0x474ecce046c99d41:0xc76f83a95070630c!2m2!1d23.129873!2d46.3065798!1m5!1m1!1s0x474ed28464e658bb:0x8b049d4bab38bf2e!2m2!1d23.0619642!2d46.307281!1m5!1m1!1s0x474ecdea7dd00b8f:0x89d345d0ed1a61ad!2m2!1d23.0657906!2d46.2726882!1m5!1m1!1s0x474eca1cedae3ebd:0xc2a91ad65c1f15d6!2m2!1d23.2244859!2d46.2252305!3e0?hl=en-US"
            }
          ],
          "images": [
            {
              "text": "<b>Poiana cu Narcise</b> - Nu culegeți multe narcise, odată rupte se ofilesc destul de rapid și își pierd mirosul ... magia lor are efect doar aici.",
              "thumbnail": "assets/img/attractions/article/narcise/thumbnail/1.jpg",
              "fullSize": "assets/img/attractions/article/narcise/fullSize/1.jpg"
            },
            {
              "text": "<b>Poiana cu Narcise</b> - Zona este înconjurată de culmi montane și păduri de conifere.",
              "thumbnail": "assets/img/attractions/article/narcise/thumbnail/2.jpg",
              "fullSize": "assets/img/attractions/article/narcise/fullSize/2.jpg"
            }
          ]
        }
      ]
    },
    {
      "type": "title",
      "text": "<i class='far fa-heart'></i> De făcut",
      "sectionId": "toDo",
      "addLinkInPageHeadline": true
    },
    {
      "type": "article",
      "specificArticles": [
        {
          "title": "<i class='fas fa-blind'></i> Tururi ghidate",
          "id": "guidedTour",
          "text": "Poți să mergi în drumeții spre atracțiile specificate mai sus dar noi îți sugerăm să le vezi împreună cu un ghid deoarece povestea contează. Roșia Montană are un trecut de aur - modul de funcționare al galeriilor, tăurilor, carierelor și a altor obiective folosite în extracția aurului, povestea clădirilor de patrimoniu sau impactul megaproiectului minier propus de firma canadiană și protestele de atunci sunt doar câteva din motivele pentru care vă recomandăm să vizitați Roșia Montana împreună cu un ghid (pe jos sau cu bicicleta). Dacă sunteți interesați de:",
          "seeAlso": [
            {
              "text": "<br><b>- trasee ghidate personalizate</b> - specificați la rezervarea unei camere și vă vom contacta telefonic - vezi aici",
              "textOnMouseOver": "Click aici...",
              "link": "ro/accommodation#bookings"
            },
            {
              "text": "<br><b>- trasee ghidate standard</b> - vezi aici pachete cu trasee ghidate propuse",
              "textOnMouseOver": "Click aici...",
              "link": "ro/events/all"
            }
          ],
          "images": [
            {
              "text": "Traseu ghidat centrul istoric Roșia Montană cu un grup din Arad.",
              "thumbnail": "assets/img/accommodation/article/guides/thumbnail/ghid-rosia-montana.jpg",
              "fullSize": "assets/img/accommodation/article/guides/fullSize/ghid-rosia-montana.jpg"
            },
            {
              "text": "Traseu ghidat spre obiective naturale și zone protejate Roșia Montană cu un grup din Germania.",
              "thumbnail": "assets/img/accommodation/article/guides/thumbnail/ghid-apuseni.jpg",
              "fullSize": "assets/img/accommodation/article/guides/fullSize/ghid-apuseni.jpg"
            },
            {
              "text": "Traseu ghidat exploatări miniere cu un grup din India.",
              "thumbnail": "assets/img/accommodation/article/guides/thumbnail/ghid-cariera.jpg",
              "fullSize": "assets/img/accommodation/article/guides/fullSize/ghid-cariera.jpg"
            }
          ]
        },
        {
          "title": "<i class='fas fa-bicycle'></i> Ciclism",
          "id": "bike",
          "text": "Ne aflăm într-o zonă cu dealuri, văi și sate apusene legate de drumuri de țară ideale de ciclism montan. Oferim biciclete de munte de închiriat sau trasee ghidate pe bicicletă. Mai jos sunt câteva din traseele pe care le-ai putea face la noi:",
          "seeAlso": [
            {
              "text": "<br><b>- Traseul Tăurilor</b> - 7km - vezi harta, profil și date gps",
              "textOnMouseOver": "Click aici...",
              "link": "https://www.bikemap.net/en/r/4121632"
            },
            {
              "text": "<br><b>- Traseul Vârtop</b> - 12km - vezi harta, profil și date gps",
              "textOnMouseOver": "Click aici...",
              "link": "https://www.bikemap.net/en/r/3594806"
            },
            {
              "text": "<br><b>- Traseul Detunata</b> - 20km - vezi harta, profil și date gps",
              "textOnMouseOver": "Click aici...",
              "link": "https://www.bikemap.net/en/r/4122612/"
            },
            {
              "text": "<br><b>- Traseul Geamăna</b> - 34km - vezi harta, profil și date gps",
              "textOnMouseOver": "Click aici...",
              "link": "https://www.bikemap.net/en/r/3873269"
            },
            {
              "text": "<br><b>- Traseul Negrileasa</b> - 39km - vezi harta, profil și date gps",
              "textOnMouseOver": "Click aici...",
              "link": "https://www.bikemap.net/en/r/3873321"
            }
          ],
          "images": [
            {
              "text": "Spre Vârtop.",
              "thumbnail": "assets/img/attractions/article/rotunduPeak/thumbnail/9.jpg",
              "fullSize": "assets/img/attractions/article/rotunduPeak/fullSize/9.jpg"
            },
            {
              "text": "Spre Geamăna.",
              "thumbnail": "assets/img/accommodation/article/guides/thumbnail/traseu_ghidat_bicicleta_geamana.jpg",
              "fullSize": "assets/img/accommodation/article/guides/fullSize/traseu_ghidat_bicicleta_geamana.jpg"
            },
            {
              "text": "Oferim biciclete de închiriat și trasee ghidate pe bicicletă cu asistență mecanică pe traseu.",
              "thumbnail": "assets/img/accommodation/article/outside/thumbnail/bikes.jpg",
              "fullSize": "assets/img/accommodation/article/outside/fullSize/bikes.jpg"
            }
          ]
        },
        {
          "title": "Tir cu arcul",
          "text": "Chiar lângă noi se află un club montan specializat în tir cu arcul ce oferă cursuri de inițiere sau perfecționare pentru adulți sau copii. Au diverse tipuri de arcuri și un teren cu ținte, special realizat pentru tir cu arcul.",
          "images": [
            {
              "text": "Cursuri de tir cu arcul Rosia Montana.",
              "thumbnail": "assets/img/accommodation/article/archery/thumbnail/tir-cu-arcul-archery-rosia-montana3.jpg",
              "fullSize": "assets/img/accommodation/article/archery/fullSize/tir-cu-arcul-archery-rosia-montana3.jpg"
            },
            {
              "text": "Cursuri de tir cu arcul Rosia Montana.",
              "thumbnail": "assets/img/accommodation/article/archery/thumbnail/tir-cu-arcul-archery-rosia-montana2.jpg",
              "fullSize": "assets/img/accommodation/article/archery/fullSize/tir-cu-arcul-archery-rosia-montana2.jpg"
            }
          ]
        },
        {
          "title": "<i class='fas fa-train'></i> Mocănița",
          "text": "<b>Mocănița cu aburi</b> era folosită în trecut pentru a transporta minerii și minereul aurifer de la unzina Gura Roșia, iar acum funcționează în scop turistic. Sunt 2 mocănițe în apropiere: <b>Mocănița Abrud - Câmpeni</b> (~10min de mers cu mașina de noi; turul durează 3 ore) și <b>Mocănița Crișcior - Brad</b> (~45min de mers cu mașina de noi; turul durează 2 ore). <br><i class='fa fa-map-signs'></i> <b>Cum ajung?</b> - ",
          "seeAlso": [
            {
              "text": "vezi harta mocănița Abrud ",
              "textOnMouseOver": "Click aici...",
              "link": "https://www.google.com/maps/dir/Casa+Petri+Rosia+Montana,+Historical+center,+nr.+331A,+Ro%C8%99ia+Montan%C4%83+517615,+Romania/Gura+Ro%C8%99iei,+Romania/Mocanita+Abrud-Campeni,+Strada+G%C4%83rii,+Abrud,+Romania/@46.2912065,23.0596886,13.22z/data=!4m20!4m19!1m5!1m1!1s0x474ecce046c99d41:0xc76f83a95070630c!2m2!1d23.129873!2d46.3065798!1m5!1m1!1s0x474ed28464e658bb:0x8b049d4bab38bf2e!2m2!1d23.0619642!2d46.307281!1m5!1m1!1s0x474ecded9cc9eb57:0x142db33519215b05!2m2!1d23.0595852!2d46.2800881!3e0?hl=en-US"
            },
            {
              "text": " | vezi harta mocănița Crișcior",
              "textOnMouseOver": "Click aici...",
              "link": "https://www.google.ro/maps/dir/Casa+Petri+Rosia+Montana,+Ro%C8%99ia+Montan%C4%83/Cri%C8%99cior/@46.2155288,22.8577319,11z/data=!3m1!4b1!4m14!4m13!1m5!1m1!1s0x474ecce046c99d41:0xc76f83a95070630c!2m2!1d23.129873!2d46.3065798!1m5!1m1!1s0x474edce95166256f:0x243ce1f1a0f481fb!2m2!1d22.866127!2d46.1234715!3e0"
            },
            {
              "text": "<br>Vezi programul mocăniței și date de contact",
              "textOnMouseOver": "Click aici...",
              "link": "http://www.cfi.ro/index.php?p=1_15"
            }
          ],
          "images": [
            {
              "text": "Cu mocănița prin Apuseni",
              "thumbnail": "assets/img/attractions/article/steamTrain/thumbnail/1.jpg",
              "fullSize": "assets/img/attractions/article/steamTrain/fullSize/1.jpg"
            },
            {
              "text": "Cu mocănița prin Apuseni",
              "thumbnail": "assets/img/attractions/article/steamTrain/thumbnail/2.jpg",
              "fullSize": "assets/img/attractions/article/steamTrain/fullSize/2.jpg"
            }
          ]
        },
        {
          "title": "La cules de...",
          "text": "Zmeură, fragi, mure, ciuperci, afine, muguri de brad și alte bunătăți puteți găsi printr-o drumeție ușoară, toamna, pe masivul Cârnic sau spre Vârtop. <br><i class='fa fa-map-signs'></i> <b>Cum ajung?</b> 1h drumeție -  ",
          "seeAlso": [
            {
              "text": "vezi harta",
              "textOnMouseOver": "Click aici...",
              "link": "https://www.google.ro/maps/dir/Masivul+C%C3%A2rnic,+Rom%C3%A2nia/Casa+Petri+Rosia+Montana,+Historical+center,+nr.+331A,+Ro%C8%99ia+Montan%C4%83+517615,+Rom%C3%A2nia/@46.3025327,23.130735,16z/data=!3m1!4b1!4m14!4m13!1m5!1m1!1s0x474ecce4eb70d119:0xa7d0d30d93d215ac!2m2!1d23.1322449!2d46.2995549!1m5!1m1!1s0x474ecce046c99d41:0xc76f83a95070630c!2m2!1d23.129873!2d46.3065798!3e2?hl=ro"
            }
          ],
          "images": [
            {
              "text": "Poiana cu Zmeură - coapte în Septembrie.",
              "thumbnail": "assets/img/attractions/article/vartop/thumbnail/12.jpg",
              "fullSize": "assets/img/attractions/article/vartop/fullSize/12.jpg"
            },
            {
              "text": "Zona cu mure - coapte în Octombrie.",
              "thumbnail": "assets/img/attractions/article/vartop/thumbnail/18.jpg",
              "fullSize": "assets/img/attractions/article/vartop/fullSize/18.jpg"
            }
          ]
        },
        {
          "title": "<i class='far fa-snowflake'></i> Sanie/ski",
          "text": "Iarna la Roșia Montană scoate la iveală peisaje de poveste cu case vechi acoperite de zăpadă și locuri ideale de dat cu sania. În apropiere se află și pârtia de ski Arieșeni. <br><i class='fa fa-map-signs'></i> <b>Cum ajung?</b> 1h cu mașina - ",
          "seeAlso": [
            {
              "text": "vezi harta",
              "textOnMouseOver": "Click aici...",
              "link": "https://www.google.ro/maps/dir/Arieseni,+Rom%C3%A2nia/Casa+Petri+Rosia+Montana,+Historical+center,+nr.+331A,+Ro%C8%99ia+Montan%C4%83+517615,+Rom%C3%A2nia/@46.3931031,22.8054491,11z/data=!3m1!4b1!4m14!4m13!1m5!1m1!1s0x4748d2262ee9e15f:0xaa4aafa3221b5e06!2m2!1d22.7666671!2d46.483333!1m5!1m1!1s0x474ecce046c99d41:0xc76f83a95070630c!2m2!1d23.129873!2d46.3065798!3e0?hl=ro"
            }
          ],
          "images": [
            {
              "text": "Cu sania pe derdelușul de langă casă.",
              "thumbnail": "assets/img/accommodation/article/outside/thumbnail/sleighing.jpg",
              "fullSize": "assets/img/accommodation/article/outside/fullSize/sleighing.jpg"
            },
            {
              "text": "La Arieșeni sunt 3 pârtii cu telescaun și teleski.",
              "thumbnail": "assets/img/attractions/article/arieseni/thumbnail/arieseni.jpg",
              "fullSize": "assets/img/attractions/article/arieseni/fullSize/arieseni.jpg"
            }
          ]
        }
      ]
    },
    {
      "type": "socialButtons"
    }
  ]
}
